uplc/__init__.py
uplc/__main__.py
uplc/ast.py
uplc/compiler_config.py
uplc/cost_model.py
uplc/flat_decoder.py
uplc/flat_encoder.py
uplc/lexer.py
uplc/machine.py
uplc/parser.py
uplc/tools.py
uplc/util.py
uplc/cost_model_files/2022-07-01/plutus-costmodels-secp256k1-3.json
uplc/cost_model_files/2023-02-14/cost-model-secp-preprod-mainnet.json
uplc/cost_model_files/2024-07-30/cost-model-merged.json
uplc/cost_model_files/base/builtinCostModel.json
uplc/cost_model_files/base/cekMachineCosts.json
uplc/cost_model_files/base/commit
uplc/optimizer/__init__.py
uplc/optimizer/deduplicate.py
uplc/optimizer/pre_apply_args.py
uplc/optimizer/pre_evaluation.py
uplc/optimizer/remove_force_delay.py
uplc/transformer/__init__.py
uplc/transformer/debrujin_variables.py
uplc/transformer/plutus_version_enforcer.py
uplc/transformer/undebrujin_variables.py
uplc/transformer/unique_variables.py
uplc-1.3.1.dist-info/METADATA
uplc-1.3.1.dist-info/WHEEL
uplc-1.3.1.dist-info/entry_points.txt
uplc-1.3.1.dist-info/licenses/LICENSE.txt
uplc-1.3.1.dist-info/RECORD
