Metadata-Version: 2.4
Name: uplc
Version: 1.3.1
Summary: Python implementation of untyped plutus language core
Project-URL: Repository, https://github.com/opshin/uplc
Author-email: nielstron <n.muendler@web.de>
License-Expression: MIT
License-File: LICENSE.txt
Keywords: cardano,compiler,language,programming-language,python,smart-contracts,validator
Classifier: Development Status :: 3 - Alpha
Classifier: Intended Audience :: Developers
Classifier: License :: OSI Approved :: MIT License
Classifier: Programming Language :: Python :: 3.9
Classifier: Programming Language :: Python :: 3.10
Classifier: Programming Language :: Python :: 3.11
Classifier: Programming Language :: Python :: 3.12
Classifier: Programming Language :: Python :: 3.13
Classifier: Programming Language :: Python :: 3.14
Classifier: Topic :: Software Development :: Assemblers
Requires-Python: <4.0,>=3.9
Requires-Dist: bitarray>=3.7.2
Requires-Dist: bitstring>=4.2.3
Requires-Dist: cbor2>=5.4.6
Requires-Dist: frozendict>=2.3.8
Requires-Dist: frozenlist2>=1.0.0
Requires-Dist: pyblst>=0.3.14
Requires-Dist: pycardano>=0.9.0
Requires-Dist: pycryptodome>=3.21.0
Requires-Dist: pynacl>=1.6.0
Requires-Dist: python-secp256k1-cardano>=0.2.4
Requires-Dist: regex>=2025.9.18
Requires-Dist: rply>=0.7.8
